AUTHORS.rst
CONTRIBUTING.rst
HISTORY.rst
LICENSE
MANIFEST.in
README.md
setup.cfg
setup.py
dia_staver.egg-info/PKG-INFO
dia_staver.egg-info/SOURCES.txt
dia_staver.egg-info/dependency_links.txt
dia_staver.egg-info/entry_points.txt
dia_staver.egg-info/not-zip-safe
dia_staver.egg-info/top_level.txt
docs/Makefile
docs/authors.rst
docs/conf.py
docs/contributing.rst
docs/history.rst
docs/index.rst
docs/installation.rst
docs/make.bat
docs/readme.rst
docs/usage.rst
docs/_static/._STAVER_pipeline.png
docs/_static/Algorithm_logo.png
docs/_static/STAVER_pipeline.png
docs/_static/cli_demo.png
staver/DIANN_quantification_rawdata.py
staver/HighCIPeptides.py
staver/MissingValueHandler.py
staver/PeptideToProteinInference.py
staver/__init__.py
staver/batch_rename.py
staver/cli.py
staver/cli_download_pride_data.py
staver/download_pride_data.py
staver/get_filename_size.py
staver/merge_data.py
staver/peptide_scoring.py
staver/protein_accumulation_plots.py
staver/protein_dynamic_range.py
staver/read_file.py
staver/staver.py
staver/staver_pipeline.py
staver/utils.py
tests/__init__.py
tests/rich_tabel.py
tests/rich_test.py
tests/test.py
tests/test_staver.py